{
  "aktualizacja": "16.07.2026 20:30",
  "alarm": {
    "strefa_1": "disarmed",
    "strefa_2": "disarmed",
    "wejscia_naruszone": []
  },
  "rekuperator": {
    "bypass": "Otwarty (auto)",
    "co2": "500.0",
    "error_code": "0.0",
    "filtry_dni": "55.0",
    "nawiew": "100.0",
    "status": "on",
    "tryb": "Tryb inteligentny",
    "wyciag": "90.0"
  },
  "temperatury": {
    "cpu_ha": "50.6",
    "czerpnia": "24.2",
    "garaz": "unavailable",
    "kotlownia": "unavailable",
    "lazienka": "26.1",
    "nagrzewnica": "0.3",
    "nawiew": "26.9",
    "parownica": "unavailable",
    "piwnica": "20.0",
    "pokoj_franka": "25.07",
    "pokoj_z_jaskolka": "25.2",
    "rekuperator": "26.9",
    "salon": "24.61",
    "salon_klima": "26",
    "stacja_1": "unavailable",
    "stacja_2": "unavailable",
    "strych": "unavailable",
    "sypialnia": "24.53",
    "sypialnia_klima": "24",
    "wiatrolap": "unavailable",
    "wyciag": "26.4",
    "wyrzutnia": "25.9",
    "zewnetrzna_polnoc": "unavailable",
    "zewnetrzna_wschod": "unavailable"
  },
  "wilgotnosc": {
    "lazienka": "64",
    "piwnica": "69",
    "powietrze": "54.0",
    "stacja": "unavailable"
  },
  "zmiekczacz": {
    "dni_do_konca": "26",
    "sol_procent": "40.0"
  }
}
